rdflib_django
