Metadata-Version: 1.0
Name: rdflib-django
Version: 0.3
Summary: Store implementation for RDFlib using Django models as its backend
Home-page: http://github.com/publysher/rdflib-django
Author: Yigal Duppen
Author-email: yigal@publysher.nl
License: MIT
Keywords: django rdf rdflib store
Platform: UNKNOWN
Classifier: Development Status :: 3 - Alpha
Classifier: Framework :: Django
Classifier: Intended Audience :: Developers
Classifier: License :: OSI Approved :: MIT License
Classifier: Operating System :: OS Independent
Classifier: Programming Language :: Python
Classifier: Programming Language :: Python :: 2.7
Classifier: Topic :: Internet :: WWW/HTTP
Classifier: Topic :: Software Development :: Libraries :: Python Modules
